politipo/__init__.py
politipo/type_converter.py
politipo/type_mapper.py
politipo-0.1.5.dist-info/METADATA
politipo-0.1.5.dist-info/WHEEL
politipo-0.1.5.dist-info/top_level.txt
politipo-0.1.5.dist-info/RECORD
