Metadata-Version: 2.4
Name: politipo
Version: 0.1.5
Summary: A library for seamless type conversions between Python data structures and models.
Author-email: Kevin Saltarelli <kevinqz@gmail.com>
Requires-Python: >=3.11
